pyseckit/__init__.py
pyseckit/cli.py
pyseckit/ci_cd/__init__.py
pyseckit/ci_cd/manager.py
pyseckit/cloud/__init__.py
pyseckit/cloud/checkov.py
pyseckit/core/config.py
pyseckit/core/exceptions.py
pyseckit/core/scanner.py
pyseckit/dast/__init__.py
pyseckit/dast/zap.py
pyseckit/integrations/__init__.py
pyseckit/integrations/elasticsearch_integration.py
pyseckit/integrations/notifications.py
pyseckit/plugins/__init__.py
pyseckit/plugins/base.py
pyseckit/plugins/registry.py
pyseckit/plugins/scanner_plugin.py
pyseckit/reporting/__init__.py
pyseckit/reporting/manager.py
pyseckit/sast/__init__.py
pyseckit/sast/bandit.py
pyseckit/sast/safety.py
pyseckit/sast/semgrep.py
pyseckit/secret_scan/__init__.py
pyseckit/secret_scan/gitleaks.py
pyseckit/secret_scan/trufflehog.py
pyseckit/threat_model/__init__.py
pyseckit/threat_model/advanced_generator.py
pyseckit/threat_model/generator.py
pyseckit/web/__init__.py
pyseckit/web/api.py
pyseckit/web/app.py
pyseckit/web/dashboard.py
secflow-1.0.0.dist-info/licenses/LICENSE
secflow-1.0.0.dist-info/METADATA
secflow-1.0.0.dist-info/WHEEL
secflow-1.0.0.dist-info/entry_points.txt
secflow-1.0.0.dist-info/top_level.txt
secflow-1.0.0.dist-info/RECORD
