Metadata-Version: 2.4
Name: secflow
Version: 1.0.0
Summary: Enterprise Security Framework for DevSecOps Integration
Author-email: SecFlow Team <team@secflow.dev>
Maintainer-email: SecFlow Team <team@secflow.dev>
License: MIT License
Project-URL: Homepage, https://github.com/WaiperOK/SecFlow
Project-URL: Documentation, https://github.com/WaiperOK/SecFlow/wiki
Project-URL: Repository, https://github.com/WaiperOK/SecFlow
Project-URL: Changelog, https://github.com/WaiperOK/SecFlow/blob/main/CHANGELOG.md
Project-URL: Bug Tracker, https://github.com/WaiperOK/SecFlow/issues
Keywords: security,sast,dast,devsecops,ci-cd,vulnerability,scanning
Classifier: Development Status :: 5 - Production/Stable
Classifier: Intended Audience :: Developers
Classifier: License :: OSI Approved :: MIT License
Classifier: Operating System :: OS Independent
Classifier: Programming Language :: Python :: 3
Classifier: Programming Language :: Python :: 3.8
Classifier: Programming Language :: Python :: 3.9
Classifier: Programming Language :: Python :: 3.10
Classifier: Programming Language :: Python :: 3.11
Classifier: Programming Language :: Python :: 3.12
Classifier: Topic :: Security
Classifier: Topic :: Software Development :: Quality Assurance
Classifier: Topic :: System :: Systems Administration
Requires-Python: >=3.8
License-File: LICENSE
Requires-Dist: requests>=2.25.0
Requires-Dist: click>=8.0.0
Requires-Dist: pydantic>=2.0.0
Requires-Dist: pyyaml>=6.0
Requires-Dist: jinja2>=3.0.0
Requires-Dist: rich>=12.0.0
Requires-Dist: python-gitlab>=3.0.0
Requires-Dist: pygithub>=1.55
Requires-Dist: boto3>=1.20.0
Requires-Dist: elasticsearch>=8.0.0
Requires-Dist: pandas>=1.3.0
Requires-Dist: plotly>=5.0.0
Requires-Dist: bandit>=1.7.0
Requires-Dist: safety>=2.0.0
Requires-Dist: checkov>=2.0.0
Requires-Dist: semgrep>=1.0.0
Requires-Dist: truffleHog>=2.0.0
Requires-Dist: gitpython>=3.1.0
Requires-Dist: psutil>=5.8.0
Requires-Dist: cryptography>=3.4.0
Requires-Dist: flask>=2.3.0
Requires-Dist: flask-cors>=4.0.0
Provides-Extra: dev
Requires-Dist: pytest>=6.0.0; extra == "dev"
Requires-Dist: pytest-cov>=2.12.0; extra == "dev"
Requires-Dist: pytest-mock>=3.6.0; extra == "dev"
Requires-Dist: black>=21.0.0; extra == "dev"
Requires-Dist: flake8>=3.9.0; extra == "dev"
Requires-Dist: mypy>=0.910; extra == "dev"
Requires-Dist: pre-commit>=2.15.0; extra == "dev"
Requires-Dist: sphinx>=4.0.0; extra == "dev"
Requires-Dist: sphinx-rtd-theme>=1.0.0; extra == "dev"
Provides-Extra: cloud
Requires-Dist: azure-identity>=1.7.0; extra == "cloud"
Requires-Dist: azure-storage-blob>=12.8.0; extra == "cloud"
Requires-Dist: google-cloud-storage>=1.42.0; extra == "cloud"
Requires-Dist: kubernetes>=18.0.0; extra == "cloud"
Provides-Extra: enterprise
Requires-Dist: ldap3>=2.9.0; extra == "enterprise"
Requires-Dist: pyjwt>=2.3.0; extra == "enterprise"
Requires-Dist: celery>=5.2.0; extra == "enterprise"
Requires-Dist: redis>=4.0.0; extra == "enterprise"
Dynamic: license-file
